tokyo_annotation/__init__.py
tokyo_annotation/facade.py
tokyo_annotation/adapter/__init__.py
tokyo_annotation/adapter/openlineage_client_facade.py
tokyo_annotation/models/__init__.py
tokyo_annotation/models/node.py
tokyo_annotation/utils/__init__.py
tokyo_annotation/utils/digraph.py
tokyo_annotation/utils/lineage.py
tokyo_annotation/utils/linked_list.py
tokyo_annotation/utils/map.py
tokyo_annotation-0.2a3.dist-info/LICENSE
tokyo_annotation-0.2a3.dist-info/METADATA
tokyo_annotation-0.2a3.dist-info/WHEEL
tokyo_annotation-0.2a3.dist-info/top_level.txt
tokyo_annotation-0.2a3.dist-info/RECORD
