Metadata-Version: 2.1
Name: tokyo-annotation
Version: 0.2a3
Summary: Tokyo Annotation
Home-page: https://github.com/dion-ricky/tokyo-annotation
Author: Dion Ricky Saputra
Author-email: code@dionricky.com
License: MIT
Project-URL: Bug Tracker, https://github.com/dion-ricky/tokyo-annotation/issues
Keywords: data annotation
Classifier: Development Status :: 2 - Pre-Alpha
Classifier: Intended Audience :: Developers
Classifier: Topic :: Software Development :: Libraries :: Python Modules
Classifier: License :: OSI Approved :: MIT License
Classifier: Programming Language :: Python :: 3.6
Classifier: Programming Language :: Python :: 3.7
Classifier: Programming Language :: Python :: 3.8
Classifier: Programming Language :: Python :: 3.9
Requires-Python: >=3.6
License-File: LICENSE
Requires-Dist: attrs (==19.3.0)
Requires-Dist: certifi (==2020.6.20)
Requires-Dist: charset-normalizer (==2.0.12)
Requires-Dist: idna (==2.10)
Requires-Dist: openlineage-python (==0.5.1)
Requires-Dist: requests (==2.24.0)
Requires-Dist: urllib3 (==1.25.10)
